simpleshare/__init__.py
simpleshare/__main__.py
simpleshare/cli.py
simpleshare/client.py
simpleshare/gui.py
simpleshare/server.py
simpleshare/util.py
simpleshare-1.3.dist-info/LICENSE
simpleshare-1.3.dist-info/METADATA
simpleshare-1.3.dist-info/WHEEL
simpleshare-1.3.dist-info/entry_points.txt
simpleshare-1.3.dist-info/top_level.txt
simpleshare-1.3.dist-info/RECORD
