Metadata-Version: 2.1
Name: simpleshare
Version: 1.3
Summary: A local file sharing utility written in Python. Uses         multicast UDP to share the list of files, and TCP to transfer the             files themselves.
Home-page: https://github.com/ssebs/simpleshare
Author: Sebastian Safari
Author-email: contact@ssebs.com
License: MIT
Platform: UNKNOWN
Classifier: License :: OSI Approved :: MIT License
Classifier: Programming Language :: Python
Classifier: Programming Language :: Python :: 3
Classifier: Programming Language :: Python :: 3.6
Classifier: Operating System :: OS Independent
Requires-Python: >=3.6.0
Requires-Dist: pyttk
